setup.py
rig_par_diagram/__init__.py
rig_par_diagram/cli.py
rig_par_diagram/diagram.py
rig_par_diagram/geometry.py
rig_par_diagram/style.py
rig_par_diagram.egg-info/.gitignore
rig_par_diagram.egg-info/PKG-INFO
rig_par_diagram.egg-info/SOURCES.txt
rig_par_diagram.egg-info/dependency_links.txt
rig_par_diagram.egg-info/entry_points.txt
rig_par_diagram.egg-info/requires.txt
rig_par_diagram.egg-info/top_level.txt