Metadata-Version: 1.0
Name: rig-par-diagram
Version: 0.0.3
Summary: A tool for generating diagrams of SpiNNaker Place & Route solutions
Home-page: https://github.com/project-rig/rig-par-diagram
Author: Jonathan Heathcote
Author-email: UNKNOWN
License: GPLv2
Keywords: spinnaker placement routing diagram cairo
Platform: UNKNOWN
